TWchat/__init__.py
TWchat/gui.py
TWchat/listBox.py
TWchat-0.0.3.dist-info/DESCRIPTION.rst
TWchat-0.0.3.dist-info/METADATA
TWchat-0.0.3.dist-info/RECORD
TWchat-0.0.3.dist-info/WHEEL
TWchat-0.0.3.dist-info/entry_points.txt
TWchat-0.0.3.dist-info/metadata.json
TWchat-0.0.3.dist-info/top_level.txt
